bottle_json_pretty/__init__.py
bottle_json_pretty-0.1.2.dist-info/LICENSE
bottle_json_pretty-0.1.2.dist-info/METADATA
bottle_json_pretty-0.1.2.dist-info/WHEEL
bottle_json_pretty-0.1.2.dist-info/top_level.txt
bottle_json_pretty-0.1.2.dist-info/RECORD
