Metadata-Version: 2.1
Name: bottle-json-pretty
Version: 0.1.2
Summary: Return pretty JSON responses from the Bottle Web Framework.
Home-page: https://github.com/jmcker/bottle-json-pretty
Author: Jack McKernan
Author-email: jmcker@outlook.com
License: MIT
Project-URL: Bug Reports, https://github.com/jmcker/bottle-json-pretty/issues
Project-URL: Source, https://github.com/jmcker/bottle-json-pretty
Keywords: bottle,json,pretty
Platform: any
Classifier: Development Status :: 4 - Beta
Classifier: Operating System :: OS Independent
Classifier: Intended Audience :: Developers
Classifier: License :: OSI Approved :: MIT License
Classifier: Programming Language :: Python :: 2.7
Classifier: Programming Language :: Python :: 3
Classifier: Programming Language :: Python :: 3.4
Classifier: Programming Language :: Python :: 3.5
Classifier: Programming Language :: Python :: 3.6
Classifier: Programming Language :: Python :: 3.7
Classifier: Framework :: Bottle
Requires-Dist: bottle
